numgrad/__init__.py
numgrad/_config.py
numgrad/_grad.py
numgrad/_graph.py
numgrad/_variable.py
numgrad/_version.py
numgrad/_vjp.py
numgrad/conftest.py
numgrad/_numpy/__init__.py
numgrad/_numpy/_array_creation.py
numgrad/_numpy/_array_manipulation.py
numgrad/_numpy/_linalg.py
numgrad/_numpy/_mathematical.py
numgrad/_numpy/_ndarray.py
numgrad/_numpy/_random.py
numgrad/_numpy/_sorting_searching_counting.py
numgrad/_numpy/_statistics.py
numgrad/_scipy/__init__.py
numgrad/_scipy/_special/__init__.py
numgrad/_utils/__init__.py
numgrad/_utils/_expand_to.py
numgrad/_utils/_has_vjp.py
numgrad/_utils/_isscalar.py
numgrad/_utils/_numerical_grad.py
numgrad/_utils/_to_array.py
numgrad/_utils/_unbroadcast.py
numgrad-0.3.0.dist-info/LICENSE
numgrad-0.3.0.dist-info/METADATA
numgrad-0.3.0.dist-info/WHEEL
numgrad-0.3.0.dist-info/top_level.txt
numgrad-0.3.0.dist-info/RECORD
