Metadata-Version: 2.1
Name: numgrad
Version: 0.3.0
Summary: Simple gradient computation library in Python
Home-page: https://github.com/ctgk/numgrad
Author: ctgk
Author-email: r1135nj54w@gmail.com
License: MIT
Requires-Python: >=3.9
License-File: LICENSE
Requires-Dist: numpy >=2
Requires-Dist: scipy
Provides-Extra: develop
Requires-Dist: matplotlib ; extra == 'develop'
Requires-Dist: scikit-image ; extra == 'develop'
Requires-Dist: scikit-learn ; extra == 'develop'
Requires-Dist: tqdm ; extra == 'develop'
Requires-Dist: pre-commit ; extra == 'develop'
Requires-Dist: pytest ; extra == 'develop'
Requires-Dist: autopep8 ; extra == 'develop'
Requires-Dist: flake8 ; extra == 'develop'
Requires-Dist: flake8-absolute-import ; extra == 'develop'
Requires-Dist: flake8-broken-line ; extra == 'develop'
Requires-Dist: flake8-builtins ; extra == 'develop'
Requires-Dist: flake8-commas ; extra == 'develop'
Requires-Dist: flake8-docstrings ; extra == 'develop'
Requires-Dist: flake8-import-order ; extra == 'develop'
Requires-Dist: flake8-multiline-containers ; extra == 'develop'
Requires-Dist: flake8-mutable ; extra == 'develop'
Requires-Dist: pep8-naming ; extra == 'develop'
Requires-Dist: sphinx ; extra == 'develop'
Requires-Dist: sphinx-rtd-theme ; extra == 'develop'
Requires-Dist: livereload ; extra == 'develop'
Requires-Dist: twine ; extra == 'develop'
